MANIFEST.in
README.rst
setup.py
botcom/__init__.py
botcom/commandbus.py
botcom.egg-info/PKG-INFO
botcom.egg-info/SOURCES.txt
botcom.egg-info/dependency_links.txt
botcom.egg-info/top_level.txt