Metadata-Version: 1.0
Name: botcom
Version: 0.0.2
Summary: command bus
Home-page: https://github.com/ostrbor/botcom
Author: Boris Ostretsov
Author-email: ostrbor@gmail.com
License: MIT
Keywords: bot command bus
Platform: UNKNOWN
